openoath/__init__.py
openoath/hello_world.py
openoath/py.typed
openoath-0.0.4.dist-info/METADATA
openoath-0.0.4.dist-info/WHEEL
openoath-0.0.4.dist-info/top_level.txt
openoath-0.0.4.dist-info/RECORD
