Metadata-Version: 2.2
Name: openoath
Version: 0.0.4
Summary: Functions to utilize the OpenOath API.
Author: Ephy Love, Senne Van Steelandt
License: MIT
Classifier: Programming Language :: Python :: 3
Classifier: Operating System :: OS Independent
Requires-Python: >=3.6
